{"id":"595675600449121","from":{"id":"100001458099624","name":"Kham Pha"},"subject":"Bài 23: ～という","message":"<p><strong>Bài 23: ～という</strong></p>\n<p> </p>\n<p>Bạn đã bao giờ nghe người Nhật nói ～というのは、～ということ　hay ベトナムという国、。。。Phải nói là người Nhật cực kì hay dùng cấu trúc này, rất nhiều câu nói dính đến という。Vậy thì という là cái gì? Thực chất nó là と言う(nói là, gọi là). Giải thích có lẽ khó hiểu hơn ví dụ:</p>\n<p> </p>\n<p>ベトナムという国(くに）は貧しい（まずしい）人が多いです。</p>\n<p>Đất nước mà tên là Việt Nam ấy có nhiều người nghèo. (Hay dịch tốt hơn thì là Đất nước Việt Nam ấy có nhiều người nghèo)</p>\n<p> </p>\n<p>サボるというのは勝手（かって）に仕事や学校などを休むことです。</p>\n<p>サボる là chỉ việc tự động nghỉ việc hoặc nghỉ học mà không có phép.</p>\n<p> </p>\n<p>約束（やくそく）を守（まも）らないということって許（ゆる）せない。</p>\n<p>Không giữ lời hứa là điều không thể chấp nhận được.</p>\n<p> </p>\n<p>Qua ví dụ ta thấy rằng cái vế đằng sau という　 sẽ giải thích thêm thông tin, thêm các đặc tính cho từ đứng trước という. Cách dùng thì từ đằng trước là dạng nguyên thể, chú ý là danh từ và tính từ な thì đừng có thêm な hay だ.</p>\n<p> </p>\n<p>Hãy nhớ nhé, cấu trúc này được dùng cực kì cực kì nhiều. Và trong bài tiếp theo chúng ta sẽ còn tiếp tục với nó với một chút mở rộng hơn.</p>\n<p> </p>\n<p>^^</p>\n<p>Kham Pha</p>","icon":"https://fbstatic-a.akamaihd.net/rsrc.php/v2/yi/r/-64q65AWgXb.png","created_time":"2013-01-24T01:02:07+0000","updated_time":"2013-03-19T05:29:13+0000","revision":628657097150971}