{"id":"628354793847868","from":{"id":"100001695345798","name":"Tyn Aki"},"subject":"Bài 80: ~際（さい）","message":"<p>Bài 80: ~際（さい）</p>\n<p> </p>\n<p>皆さん、こんばんは!!＾＾</p>\n<p> </p>\n<p>Hôm nay mình xin giới thiệu mọi người cấu trúc ～際</p>\n<p> </p>\n<p>Đầu tiên chúng ta cùng xem ví dụ</p>\n<p> </p>\n<p>1. 証明書（しょうめいしょ）を申請（しんせい）する際は印鑑（いんかん）が必要（ひつよう）だ。</p>\n<p>Khi đăng ký thẻ chứng minh nhân dân thì cần con dấu.</p>\n<p> </p>\n<p>2.お引っ越し（ひっこし）の際の手続き（てつづき）についてはホームページをご覧（らん）ください</p>\n<p>Khi làm thủ tục chuyển nhà,để biết thêm chi tiết hãy xem trang chủ sau.</p>\n<p> </p>\n<p>Qua ví dụ chúng ta có thể hiểu ～際 dùng trong trường hợp: Khi ta làm cái này, Khi ta làm cái nọ. Nó có nghĩa tương với cấu trúc ～とき、tuy nhiên cấu trúc này ko dùng trong văn nói ,chúng ta thường gặp trong các văn bản,tài liệu chính thức(公文書）、các tờ poster.</p>\n<p> </p>\n<p>Cách chia thể: Vる　　+ 際</p>\n<p>Vた　　　　　　　N(の）+　際</p>\n<p> </p>\n<p>皆さん，よい週を</p>\n<p> </p>\n<p>Nguyễn Tuấn Vũ</p>","icon":"https://fbstatic-a.akamaihd.net/rsrc.php/v2/yi/r/-64q65AWgXb.png","created_time":"2013-03-18T14:15:17+0000","updated_time":"2013-03-18T14:15:17+0000","revision":628354790514535}