{"id":"229244010425617_650874874929193","type":"photo","object_id":"166837030148511","picture":"https://fbcdn-photos-c-a.akamaihd.net/hphotos-ak-prn1/t1.0-0/941772_166837030148511_2069221825_s.jpg","link":"https://www.facebook.com/photo.php?fbid=166837030148511&set=gm.650874874929193&type=1&relevant_count=1","from":{"id":"100004666446749","name":"Jouzu Waei"},"message":"今日は「鼻」に関する言い方を読んで超面白かったと思います。練習しましょうね。","created_time":"2013-05-07T16:27:54+0000","updated_time":"2013-05-07T16:27:54+0000","likes":{"data":{"100002290906582":{"id":"100002290906582","name":"Kanashimi No Yukue"},"100005595790015":{"id":"100005595790015","name":"いのしし 大好きなひと"},"100001609833418":{"id":"100001609833418","name":"Tsunami Hime"},"100001695345798":{"id":"100001695345798","name":"Tyn Aki"},"100000293174570":{"id":"100000293174570","name":"Vịt Vụng Về"},"100004556712097":{"id":"100004556712097","name":"Chishi Jung"},"100001231404357":{"id":"100001231404357","name":"Quoc Anh"},"1392762854":{"id":"1392762854","name":"Đỗ Minh Thu"},"100000096928751":{"id":"100000096928751","name":"Lê Linh"}},"paging":{"cursors":{"after":"MTAwMDAyMjkwOTA2NTgy","before":"MTAwMDAyMjkwOTA2NTgy"},"next":"https://graph.facebook.com/229244010425617_650874874929193/likes?limit=1&summary=1&after=MTAwMDAyMjkwOTA2NTgy"},"summary":{"total_count":10}},"comments":{"data":[]}}