{"id":"229244010425617_653932984623382","type":"link","picture":"https://fbcdn-profile-a.akamaihd.net/hprofile-ak-ash3/t1.0-1/c15.8.100.100/945330_328385177289315_1326817636_s.jpg","link":"https://www.facebook.com/gjobsvn/posts/330388163755683","from":{"id":"1582652177","name":"Vo Ngoc"},"message":"Bạn KẾ TOÁN nào biết tiếng Nhật thì liên hệ với mình ngay nhé. Cơ hội được làm việc trong Công ty Nhật để phát triển kỹ năng và nhận benefit cao rất hấp dẫn đấy.\n\nNếu bạn thực sự thấy thông tin này hữu ích, hãy chia sẻ cho bạn bè và LIKE page để cùng đón nhận những cơ hội mới nhé bạn :)","created_time":"2013-05-14T11:01:37+0000","updated_time":"2013-05-14T12:51:01+0000","likes":{"data":{"100005783684423":{"id":"100005783684423","name":"Chan Hi"},"100003669292626":{"id":"100003669292626","name":"Nhok Xinh"},"100005478454231":{"id":"100005478454231","name":"Maruko Chan"},"100002497904326":{"id":"100002497904326","name":"Min Mập"},"100000747635624":{"id":"100000747635624","name":"Nguyễn Xuân Đại"},"100003402699439":{"id":"100003402699439","name":"Trang Chan"}},"paging":{"cursors":{"after":"MTAwMDA1NzgzNjg0NDIz","before":"MTAwMDA1NzgzNjg0NDIz"},"next":"https://graph.facebook.com/229244010425617_653932984623382/likes?limit=1&summary=1&after=MTAwMDA1NzgzNjg0NDIz"},"summary":{"total_count":6}},"comments":{"data":{"653971141286233":{"id":"653971141286233","from":{"id":"100003984650164","name":"Phuong Thanh Dang"},"message":"ôi tiếc quá mỗi tội chưa học xong :3 :3","can_remove":false,"created_time":"2013-05-14T12:51:01+0000","like_count":0,"user_likes":false}},"paging":{"cursors":{"after":"NjUzOTcxMTQxMjg2MjMz","before":"NjUzOTcxMTQxMjg2MjMz"}},"summary":{"order":"chronological","total_count":1}}}