{"id":"229244010425617_746239678726045","type":"status","from":{"id":"100005801442456","name":"An Nguyen"},"message":"Động đất 7.1 độ tại khu vực Đông Bắc Nhật Bản, tâm gần Fukushima.Tại tokyo chỉ cảm nhận khoảng 4 độ, đã dỡ bỏ cảnh báo sóng thần. Fukushima là nơi đặt nhà máy điện hạt nhân từng bị phá hủy bởi sóng thần năm 2011, nếu mà dính quả nữa là hơi bị gay go.Có lẽ bạn nào mà muốn học đại học thì có lẽ chọn đại học Fukushima cũng là ý hay, nếu đủ can đảm! Hồi trước học sinh về hết nên mức đầu vào trường này có giảm chút. Hình như nó là trường quốc lập thì phải(?)\n\nSẵn đây nói luôn, đọc tin này chắc cũng có bạn sẽ lên lớp hay tới chỗ làm mà thông báo kiểu như thế này \" あぶない！国へ帰ろう\", biết là chỉ đùa thôi nhưng cái miệng nó hại cái thân mà chẳng biết! Trận động đất trước đây ! Đa số học sinh trung quốc bỏ về hết , các nhà máy, công ty cứ phải gọi là khó khăn tột cùng. Động đất thì đầu tiên người ta sẽ tích trữ nước sau đó là khăn giấy và thức ăn! Bởi thế các nhà máy cơm hộp cứ phải là hoạt động cháy máy! Thế nhưng người đâu mà làm?!? Bởi thế mà có nói ra thì họ coi chẳng khác gì người Trung quốc!\n\nNhững anh chị người Việt senpai học ở tohoku nhiều người rất nhiệt tình, không bỏ về mà ở lại làm các công việc từ thiện cũng như chăm sóc những người đi lánh nạn khắp nơi đổ về bởi đại sứ quán Việt Nam ứ thấy đâu =)) mãi dùng các kiểu mới mò tới..\nThay vì nói cái câu vô nghĩa trên, các bạn nên nói với họ ( những người Nhật ) đại loại : tôi sẽ không về dù có động đất, tôi được đi học , tôi được đi làm ở đây  nên nếu có khó khăn mà tôi bỏ về thì rất .. Kì kục! 1 lời nói không mất tiền mua , về hay không tuỳ ở bạn nhưng    Khôn nhau ở cái miệng, lời nói dối nhưng không hại ai mà ngược lại thì là 1 lời nói dối \" ngọt ngào \",vừa tốt cho hình ảnh người Việt vừa tốt cho chính bản thân chính bạn!","created_time":"2013-10-25T20:43:10+0000","updated_time":"2013-10-26T10:16:46+0000","likes":{"data":{"100000215142696":{"id":"100000215142696","name":"Tăng Anh Thư"},"100003733581822":{"id":"100003733581822","name":"Tàu Lu"},"100005620360063":{"id":"100005620360063","name":"Hoat Chung"},"100003209695375":{"id":"100003209695375","name":"Le Thien Nhi"},"100002793054191":{"id":"100002793054191","name":"Lai Vuong"},"100001416272263":{"id":"100001416272263","name":"Mai PB"},"100003016747298":{"id":"100003016747298","name":"Minh Phượng"},"100005211189763":{"id":"100005211189763","name":"Oliveu Cchann"},"100002421205294":{"id":"100002421205294","name":"Nghèo Kệ Tôi"},"657157297":{"id":"657157297","name":"Phan Dien"},"1416265619":{"id":"1416265619","name":"Starwar Bbj"},"1822854513":{"id":"1822854513","name":"Sữa Chua Không Đường"},"100006794583161":{"id":"100006794583161","name":"Anh Thắng"},"100005417492772":{"id":"100005417492772","name":"Kim Yến"},"100001594722256":{"id":"100001594722256","name":"Viết An Phạm"},"100001771155076":{"id":"100001771155076","name":"Dương Thuỷ"},"100002982264086":{"id":"100002982264086","name":"Danh Huong"},"100001531816305":{"id":"100001531816305","name":"Mẫn Nghi"},"1250876107":{"id":"1250876107","name":"Kim Hoan"},"100004362480675":{"id":"100004362480675","name":"Đi Tìm Thất Bại"},"100005173359642":{"id":"100005173359642","name":"Vu Mui"},"1305472811":{"id":"1305472811","name":"Tuan Nguyen"},"100002327743510":{"id":"100002327743510","name":"Tuan Thanh"},"100005903373573":{"id":"100005903373573","name":"HaLinh Phong Phan"},"100005478454231":{"id":"100005478454231","name":"Maruko Chan"},"100001458099624":{"id":"100001458099624","name":"Kham Pha"},"100000219148071":{"id":"100000219148071","name":"Anh Còi"},"100000776461179":{"id":"100000776461179","name":"Jotaro Nguyen"},"100000473889720":{"id":"100000473889720","name":"Ngọc Trung"},"100003188540285":{"id":"100003188540285","name":"Đầu Gấu Xấu Trai"},"1840348734":{"id":"1840348734","name":"Anh Đậu Béo"},"100004529465617":{"id":"100004529465617","name":"Nga Nguyen"},"100003822434250":{"id":"100003822434250","name":"Sói Đây Gà Đâu"},"100000971073873":{"id":"100000971073873","name":"Nam Trinh"},"100003957878204":{"id":"100003957878204","name":"Ma Kết"},"798546542":{"id":"798546542","name":"Peco Daydreamer"},"100006157633371":{"id":"100006157633371","name":"Hạt Cát"},"100002629655875":{"id":"100002629655875","name":"Đỗ Thế Phong"},"100006102422065":{"id":"100006102422065","name":"Cókhônggiữ Mấtđừngtìm"},"100003013864105":{"id":"100003013864105","name":"Thu Trang"},"100003913383051":{"id":"100003913383051","name":"Tho Tran"},"100001079726837":{"id":"100001079726837","name":"Hatenai Yume"},"100002855090345":{"id":"100002855090345","name":"Xuan Huy"},"100002607997537":{"id":"100002607997537","name":"Trần Đức Chiến"},"100004234301106":{"id":"100004234301106","name":"Hà Kawaii"},"100001628612184":{"id":"100001628612184","name":"Mai Tròn"},"100004393294754":{"id":"100004393294754","name":"Le Chi Phan"},"100003981681171":{"id":"100003981681171","name":"Moon Sún"},"100000020988042":{"id":"100000020988042","name":"Viet Huong Nguyen"},"100003291701878":{"id":"100003291701878","name":"Bui Anhdat"},"100004055040287":{"id":"100004055040287","name":"Nguyễn Minh"},"100002989231451":{"id":"100002989231451","name":"Nguyen Son Ha"},"100000435036779":{"id":"100000435036779","name":"Hiep Dao Xuan"},"100003837141956":{"id":"100003837141956","name":"Mai Hoàng"},"100004009345656":{"id":"100004009345656","name":"Hung Trinh"},"100004743935020":{"id":"100004743935020","name":"Thanh Huyen"},"100004450956167":{"id":"100004450956167","name":"Thắng Satoh"},"100004411770431":{"id":"100004411770431","name":"Giap Viet Dung"},"100001438932250":{"id":"100001438932250","name":"Luong Anh Nguyet"},"100003726227911":{"id":"100003726227911","name":"Hoang Nguyen Huy"},"100003941338766":{"id":"100003941338766","name":"Nhinl Pe"},"100002869230720":{"id":"100002869230720","name":"Linh Nguyen Van"}},"paging":{"cursors":{"after":"MTAwMDAwMjE1MTQyNjk2","before":"MTAwMDAwMjE1MTQyNjk2"},"next":"https://graph.facebook.com/229244010425617_746239678726045/likes?limit=1&summary=1&after=MTAwMDAwMjE1MTQyNjk2"},"summary":{"total_count":64}},"comments":{"data":{"746290842054262":{"id":"746290842054262","from":{"id":"100004055040287","name":"Nguyễn Minh"},"message":"Khôn ở cái miệng\nHay cho câu nói này","can_remove":false,"created_time":"2013-10-25T23:21:40+0000","like_count":0,"user_likes":false},"746291448720868":{"id":"746291448720868","from":{"id":"100003291701878","name":"Bui Anhdat"},"message":"Thằng bạn em ms bay sang hjroshjma không biết bên ấy thế nào lỗ động đất cái thì tội","can_remove":false,"created_time":"2013-10-25T23:23:43+0000","like_count":0,"user_likes":false},"746355282047818":{"id":"746355282047818","from":{"id":"100005903373573","name":"HaLinh Phong Phan"},"message":"cong nhn la di dau nguoi ta cung ac cam voi nguoi Viet...nen chung ta hay cung nhau cai thien nhung anh mat ac cam do...cam on ban","can_remove":false,"created_time":"2013-10-26T02:18:59+0000","like_count":0,"user_likes":false},"746373678712645":{"id":"746373678712645","from":{"id":"100001622486348","name":"Tuan Lam"},"message":"song chet co so  di dau cung chet","can_remove":false,"created_time":"2013-10-26T03:15:01+0000","like_count":0,"user_likes":false},"746504652032881":{"id":"746504652032881","from":{"id":"100004398127401","name":"Đứng Dậy Vươn Vai"},"message":"Chuẩn luôn bạn ơi sống chết có số","can_remove":false,"created_time":"2013-10-26T10:16:46+0000","like_count":0,"user_likes":false}},"paging":{"cursors":{"after":"NzQ2MjkwODQyMDU0MjYy","before":"NzQ2MjkwODQyMDU0MjYy"},"next":"https://graph.facebook.com/229244010425617_746239678726045/comments?limit=1&summary=1&after=NzQ2MjkwODQyMDU0MjYy"},"summary":{"order":"chronological","total_count":6}}}