{"id":"229244010425617_813483105335035","from":{"name":"Red River","id":"100007590570731"},"to":{"data":[{"name":"Cộng đồng Việt Nhật ( Vietnam-Japan community )","id":"229244010425617"}]},"message":"Chúc mọi người một tuần làm việc mới vui vẻ, năng xuất và hiệu quả nhé!","actions":[{"name":"Like","link":"http://www.facebook.com/229244010425617/posts/813483105335035"}],"privacy":{"value":""},"type":"status","created_time":"2014-02-10T01:27:48+0000","updated_time":"2014-02-10T01:27:48+0000","likes":{"100000019126977":{"id":"100000019126977","name":"Nguyen Thi Ngoc Anh"},"100003291701878":{"id":"100003291701878","name":"Bui Anhdat"},"100003283330206":{"id":"100003283330206","name":"Nguyễn Sang"}},"comments":[]}