{"id":"229244010425617_842695789080433","type":"photo","object_id":"717547754934598","picture":"https://fbcdn-photos-b-a.akamaihd.net/hphotos-ak-prn1/t1.0-0/10013347_717547754934598_1133462117_s.jpg","link":"https://www.facebook.com/photo.php?fbid=717547754934598&set=gm.842695789080433&type=1&relevant_count=1","from":{"id":"100000381394367","name":"Thành Nguyễn"},"message":"Khi mà những điều có thể trông đợi được bị giảm về con số không thì con người mới thực sự trân trọng những gì mà mình đang có.\n\n期待値がゼロまで下がれば、自分に今あるものすべてに間違いなく感謝の念が\n湧く\n\n(きたいち)が(ぜろ)まで(さ)がれば、(じぶん)に(いま)あるものすべてに(まちが)いなく(かんしゃ)のねんがわく\n\nKitaichi ga zero made sagareba, jibun ni ima aru mono subete ni machigainaku kansha no nen ga waku\n\nChữ Hán\n\n期待値: Kỳ đãi trị\n\n自分: Tự phân \n\n今: Kim \n\n間違: Gian vi\n\n感謝: Cảm tạ \n\n念: Niệm \n\n湧: Dũng","created_time":"2014-03-31T10:09:01+0000","updated_time":"2014-03-31T10:09:01+0000","likes":{"data":{"100005602539708":{"id":"100005602539708","name":"Minh Chien Tran"},"100002348937847":{"id":"100002348937847","name":"Xanh Le Te"},"100002360771722":{"id":"100002360771722","name":"Missing Piece"},"100001057467030":{"id":"100001057467030","name":"Buông Tay"},"100002097793263":{"id":"100002097793263","name":"Lê Hoa"},"100001754136107":{"id":"100001754136107","name":"Nguyễn Tuấn Vũ"},"100000089472724":{"id":"100000089472724","name":"Duy Nguyen"},"100003632114986":{"id":"100003632114986","name":"Tài Tử Tế"},"100000221147466":{"id":"100000221147466","name":"Kiệt Nguyễn"},"100006734168968":{"id":"100006734168968","name":"Tiểu Nhân Mã"},"100002984557771":{"id":"100002984557771","name":"Hau Dao"}},"paging":{"cursors":{"after":"MTAwMDA1NjAyNTM5NzA4","before":"MTAwMDA1NjAyNTM5NzA4"},"next":"https://graph.facebook.com/229244010425617_842695789080433/likes?limit=1&summary=1&after=MTAwMDA1NjAyNTM5NzA4"},"summary":{"total_count":11}},"comments":{"data":[]}}