{"id":"229244010425617_847371578612854","type":"status","from":{"id":"100003913932250","name":"Khánh Phúc"},"message":"chia hàng hay bốc vác cho compini..lm từ 10:00 đêm đến 7:00 sáng...kiuke 1 tiếng...lương 1025 . E nên đi làm ko ACE ?","created_time":"2014-04-07T22:16:42+0000","updated_time":"2014-04-08T14:55:25+0000","likes":{"data":{"100006540074402":{"id":"100006540074402","name":"Chu Minh Trường"},"100000471304298":{"id":"100000471304298","name":"Nguyen Xuan Cong"},"100004717171635":{"id":"100004717171635","name":"Nguyễn Đức Duy"},"100000176631338":{"id":"100000176631338","name":"Hà Phương"},"100007066988314":{"id":"100007066988314","name":"Viet Tran"},"100001958220978":{"id":"100001958220978","name":"Trung Hiếu Bắp"},"100003181743412":{"id":"100003181743412","name":"Pham Kha"},"100003961479659":{"id":"100003961479659","name":"Giang Beo"},"100006035258468":{"id":"100006035258468","name":"Thảo Còi"},"100004090172449":{"id":"100004090172449","name":"Hãy Đợi Đấy"},"100004057374771":{"id":"100004057374771","name":"Sao Bang Vo Tinh"},"100003276696481":{"id":"100003276696481","name":"Viet Đong"},"100004079252921":{"id":"100004079252921","name":"Tình Yesterday"},"100002918208166":{"id":"100002918208166","name":"Quan Okmen"},"100003069246142":{"id":"100003069246142","name":"Hồng Trịnh"}},"paging":{"cursors":{"after":"MTAwMDA2NTQwMDc0NDAy","before":"MTAwMDA2NTQwMDc0NDAy"},"next":"https://graph.facebook.com/229244010425617_847371578612854/likes?limit=1&summary=1&after=MTAwMDA2NTQwMDc0NDAy"},"summary":{"total_count":15}},"comments":{"data":{"847372808612731":{"id":"847372808612731","from":{"id":"100007917634982","name":"Cry Cry"},"message":"K nặng lắm :)) làm đc thì làm","can_remove":false,"created_time":"2014-04-07T22:20:03+0000","like_count":0,"user_likes":false},"847374691945876":{"id":"847374691945876","from":{"id":"100003069246142","name":"Hồng Trịnh"},"message":"Bạn có muốn làm ko","can_remove":false,"created_time":"2014-04-07T22:25:46+0000","like_count":0,"user_likes":false},"847375281945817":{"id":"847375281945817","from":{"id":"100007917634982","name":"Cry Cry"},"message":"Mình á :3","can_remove":false,"created_time":"2014-04-07T22:28:07+0000","like_count":0,"user_likes":false},"847377435278935":{"id":"847377435278935","from":{"id":"100008112094651","name":"Giap Le"},"message":"Ok","can_remove":false,"created_time":"2014-04-07T22:35:54+0000","like_count":0,"user_likes":false},"847377591945586":{"id":"847377591945586","from":{"id":"100008112094651","name":"Giap Le"},"message":"O dau vay","can_remove":false,"created_time":"2014-04-07T22:36:18+0000","like_count":1,"user_likes":false},"847378335278845":{"id":"847378335278845","from":{"id":"100004478287906","name":"Lê Đức Anh"},"message":"Quan trọng tuần đc mấy buổi","can_remove":false,"created_time":"2014-04-07T22:37:54+0000","like_count":0,"user_likes":false},"847378345278844":{"id":"847378345278844","from":{"id":"100006502552041","name":"Xấu Xí"},"message":"Làm ở đâu vậy","can_remove":false,"created_time":"2014-04-07T22:37:55+0000","like_count":0,"user_likes":false},"847379738612038":{"id":"847379738612038","from":{"id":"100003069246142","name":"Hồng Trịnh"},"message":"Bn khánh phúc í. Chứ hỏi mọi ng thì ...","can_remove":false,"created_time":"2014-04-07T22:42:40+0000","like_count":1,"user_likes":false},"847379828612029":{"id":"847379828612029","from":{"id":"100003069246142","name":"Hồng Trịnh"},"message":"Việc của mình thì m qđ chứ","can_remove":false,"created_time":"2014-04-07T22:43:09+0000","like_count":0,"user_likes":false},"847383365278342":{"id":"847383365278342","from":{"id":"100006638161405","name":"Daisukina Hito"},"message":"Ở đâu thế","can_remove":false,"created_time":"2014-04-07T22:51:01+0000","like_count":1,"user_likes":false},"847383415278337":{"id":"847383415278337","from":{"id":"100006638161405","name":"Daisukina Hito"},"message":"Mình đang cần việc","can_remove":false,"created_time":"2014-04-07T22:51:07+0000","like_count":2,"user_likes":false},"847387588611253":{"id":"847387588611253","from":{"id":"100007656991195","name":"Linh Chi"},"message":"Lương qua hakken b ạ","can_remove":false,"created_time":"2014-04-07T23:04:22+0000","like_count":1,"user_likes":false},"847388571944488":{"id":"847388571944488","from":{"id":"100004087053647","name":"Đặng Ngọc Biên"},"message":"Đừng đi vào.ở nhà mà ngủ cho sướng","can_remove":false,"created_time":"2014-04-07T23:07:27+0000","like_count":0,"user_likes":false},"847401335276545":{"id":"847401335276545","from":{"id":"100003913932250","name":"Khánh Phúc"},"message":"Mất 3,5-4 lá shokai cơ","can_remove":false,"created_time":"2014-04-07T23:43:27+0000","like_count":0,"user_likes":false},"847401491943196":{"id":"847401491943196","from":{"id":"100003913932250","name":"Khánh Phúc"},"message":"Làm ở ga gyotoku , e ms sag e sợ bị lừa","can_remove":false,"created_time":"2014-04-07T23:44:05+0000","like_count":0,"user_likes":false},"847411778608834":{"id":"847411778608834","from":{"id":"100004005830479","name":"Lam School"},"message":"Compini mà phải bốc vác à.gió máy ở đâu đây","can_remove":false,"created_time":"2014-04-08T00:21:01+0000","like_count":1,"user_likes":false},"847412158608796":{"id":"847412158608796","from":{"id":"100001416272263","name":"Mai PB"},"message":"Shokai nên nếu sau 1 tuần nó bảo khg cần nữa thì đắng họng. Qua shokai là có khả năng bị lừa, hỏi ở đây ai biết ai chịu trách nhiệm hộ?","can_remove":false,"created_time":"2014-04-08T00:22:53+0000","like_count":2,"user_likes":false},"847412591942086":{"id":"847412591942086","from":{"id":"100004005830479","name":"Lam School"},"message":"Nói thôi đã biết bị lừa.compini mà phải bốc hàng.nói xếp đồ còn nghe đc.","can_remove":false,"created_time":"2014-04-08T00:24:29+0000","like_count":1,"user_likes":false},"847412765275402":{"id":"847412765275402","from":{"id":"100003913932250","name":"Khánh Phúc"},"message":"Dạ vâng. Qua thằng ng nepan j đó. Có ng dẫn e ra đó, tin tưởng đc ko ace ơi","can_remove":false,"created_time":"2014-04-08T00:25:17+0000","like_count":0,"user_likes":false},"847413041942041":{"id":"847413041942041","from":{"id":"100003913932250","name":"Khánh Phúc"},"message":"Hnay đưa tiền trc , ko biết bjo mới đc làm , hô","can_remove":false,"created_time":"2014-04-08T00:26:22+0000","like_count":0,"user_likes":false},"847413171942028":{"id":"847413171942028","from":{"id":"100004005830479","name":"Lam School"},"message":"Nghe giọng biết moi bò qua.anh đc mấy tháng r","can_remove":false,"created_time":"2014-04-08T00:26:53+0000","like_count":1,"user_likes":false},"847413425275336":{"id":"847413425275336","from":{"id":"100003913932250","name":"Khánh Phúc"},"message":"Vâng, sang đc tuần thôi ak , nên e biết j đâu, đang cần aec nhà m tư vấn giúp đỡ mà","can_remove":false,"created_time":"2014-04-08T00:28:03+0000","like_count":0,"user_likes":false},"847413821941963":{"id":"847413821941963","from":{"id":"100003069255510","name":"Viên Đá Nhỏ"},"message":"mới sang cứ nghỉ ngơi đi bạn","can_remove":false,"created_time":"2014-04-08T00:29:37+0000","like_count":1,"user_likes":false},"847413845275294":{"id":"847413845275294","from":{"id":"100004005830479","name":"Lam School"},"message":"Học đê.chưa đâu vào đâu đã Lm.vs chả ăn.cứ hưởng thụ nốt đi.cảm nhận nốt mùi vn còn dính lại đê.","can_remove":false,"created_time":"2014-04-08T00:29:41+0000","like_count":1,"user_likes":false},"847414148608597":{"id":"847414148608597","from":{"id":"100004005830479","name":"Lam School"},"message":"Sang đây mang theo tinh thần lm giàu à.ms có 1 tuần mà đã .....","can_remove":false,"created_time":"2014-04-08T00:30:35+0000","like_count":0,"user_likes":false},"847415081941837":{"id":"847415081941837","from":{"id":"100003913932250","name":"Khánh Phúc"},"message":"À, thì cơ hội có mà ko nắm lấy sau này biết lsao ạ","can_remove":false,"created_time":"2014-04-08T00:33:06+0000","like_count":0,"user_likes":false},"847415205275158":{"id":"847415205275158","from":{"id":"100004005830479","name":"Lam School"},"message":"Thế đi Lm đi.","can_remove":false,"created_time":"2014-04-08T00:33:31+0000","like_count":0,"user_likes":false},"847415948608417":{"id":"847415948608417","from":{"id":"100003913932250","name":"Khánh Phúc"},"message":"Thôi, e ăn chơi nghỉ ngơi đã, hỏi ý kiến m. Ng tí","can_remove":false,"created_time":"2014-04-08T00:35:54+0000","like_count":0,"user_likes":false},"847418135274865":{"id":"847418135274865","from":{"id":"100005898276999","name":"Kí Ức Buồn"},"message":"1025¥/1h à.","can_remove":false,"created_time":"2014-04-08T00:43:12+0000","like_count":1,"user_likes":false},"847425825274096":{"id":"847425825274096","from":{"id":"100004394893221","name":"NùnBẹt Vu"},"message":"Ngon . Bắt đầu thành trâu r ku. Nhung ma k hoc thì nhục lắm","can_remove":false,"created_time":"2014-04-08T01:05:16+0000","like_count":1,"user_likes":false},"847427235273955":{"id":"847427235273955","from":{"id":"100007917634982","name":"Cry Cry"},"message":"Du học sinh làm qua hakken thì cẩn thận :) mình mới thấy mấy ng bị về nc vì Nhật no soi hakken nhiều","can_remove":false,"created_time":"2014-04-08T01:08:35+0000","like_count":1,"user_likes":false},"847427241940621":{"id":"847427241940621","from":{"id":"100003913932250","name":"Khánh Phúc"},"message":"Phải học chứ ạ, đó là e hỏi ý kiến thôi","can_remove":false,"created_time":"2014-04-08T01:08:36+0000","like_count":0,"user_likes":false},"847427745273904":{"id":"847427745273904","from":{"id":"100003913932250","name":"Khánh Phúc"},"message":"Vâng . ACE sang trc nên hiểu, có j tư vấn thẳng thắn cho e","can_remove":false,"created_time":"2014-04-08T01:10:13+0000","like_count":0,"user_likes":false},"847441405272538":{"id":"847441405272538","from":{"id":"100005898276999","name":"Kí Ức Buồn"},"message":"Ngày tớ vẫn chơi 11 tiếng zutto như thường 1020¥/1h","can_remove":false,"created_time":"2014-04-08T01:47:58+0000","like_count":0,"user_likes":false},"847776268572385":{"id":"847776268572385","from":{"id":"100008112094651","name":"Giap Le"},"message":"Minh o tokyo","can_remove":false,"created_time":"2014-04-08T14:54:51+0000","like_count":0,"user_likes":false},"847776498572362":{"id":"847776498572362","from":{"id":"100008112094651","name":"Giap Le"},"message":"Gan thap tokyo thawa","can_remove":false,"created_time":"2014-04-08T14:55:25+0000","like_count":1,"user_likes":false}},"paging":{"cursors":{"after":"ODQ3MzcyODA4NjEyNzMx","before":"ODQ3MzcyODA4NjEyNzMx"},"next":"https://graph.facebook.com/229244010425617_847371578612854/comments?limit=1&summary=1&after=ODQ3MzcyODA4NjEyNzMx"},"summary":{"order":"chronological","total_count":36}}}